[
    {
        "publisher": "영진닷컴",
        "description": "여러분의 데이터 분석 공부를 재미있게!유튜브 누적 130만 view의 슬기로운통계생활이 수험서 전문 브랜드 이기적과 함께 빅데이터분석기사 실기 합격을 위한 기본서를 출간하였다.본 도서는 데이터산업진흥원의 최신 출제기준을 적용하였으며, 빅데이터분석기사 실기 시험의 최신 경향을 철저히 분석하고 설명한 완벽 대비서이다.꼼꼼한 기초 이론과 코드 설명으로 비전공자, 입문자도 혼자 학습할 수 있도록 안내하고 있으며, 최신 기출문제를 수록하여 실전에 철저히 대비할 수 있도록 하였다. 또한 시험의 핵심을 다루는 무료 동영상도 제공하여, 합격을 위한 모든 노하우를 얻을 수 있다.독자 소통을 위한 전용 채널 statple.com/go/bae도 개설되었으므로 빅분기 시험을 준비한다면 꼭 방문해보자.",
        "title": "2025 이기적 빅데이터분석기사 실기 Python (최신 기출문제 수록 + 동영상 강의 무료 제공)",
        "author": "이삭^김상돈",
        "image": "https://shopping-phinf.pstatic.net/main_5362486/53624865956.20250320071555.jpg",
        "isbn": "9788931477191",
        "discount": "28800",
        "link": "https://search.shopping.naver.com/book/catalog/53624865956",
        "pubdate": "20250411"
    },
    {
        "publisher": "CRC Press",
        "description": "The book, \"Python - A Practical Learning Approach,\" exemplifies Python's simplicity and versatility with numerous examples, ensuring a seamless learning journey. Beyond theory, the language's practicality allows learners to actively apply their knowledge in real-world scenarios, establishing Python as an asset in education.",
        "title": "Python (A Practical Learning Approach)",
        "author": "",
        "image": "https://shopping-phinf.pstatic.net/main_4924873/49248739619.20240719124041.jpg",
        "isbn": "9781032712642",
        "discount": "255150",
        "link": "https://search.shopping.naver.com/book/catalog/49248739619",
        "pubdate": "20240807"
    },
    {
        "publisher": "CRC Press",
        "description": "The book, \"Python - A Practical Learning Approach,\" exemplifies Python's simplicity and versatility with numerous examples, ensuring a seamless learning journey. Beyond theory, the language's practicality allows learners to actively apply their knowledge in real-world scenarios, establishing Python as an asset in education.",
        "title": "Python (A Practical Learning Approach)",
        "author": "",
        "image": "https://shopping-phinf.pstatic.net/main_4924874/49248746618.20240719124043.jpg",
        "isbn": "9781032712666",
        "discount": "102030",
        "link": "https://search.shopping.naver.com/book/catalog/49248746618",
        "pubdate": "20240807"
    },
    {
        "publisher": "복두출판사",
        "description": "김강현의 『코딩입문 PYTHON』은 〈파이썬 개요1.1 파이썬 소개〉, 〈파이썬을 위한 프로그램 설치2.1 파이썬 설치하기〉, 〈파이썬 시작!3.1 파이썬의 기초, 화면에 출력하기 〉 등에 대한 기초적이고 전반적인 내용이 수록된 책이다.",
        "title": "코딩입문 PYTHON (미래를 듣다)",
        "author": "김강현",
        "image": "https://shopping-phinf.pstatic.net/main_5382810/53828101185.20250330072037.jpg",
        "isbn": "9791166756030",
        "discount": "25200",
        "link": "https://search.shopping.naver.com/book/catalog/53828101185",
        "pubdate": "20250325"
    },
    {
        "publisher": "Ladoo Publishing LLC",
        "description": "Are you thinking about learning how to use the Python programming language? Thinking about getting started on a programming career?Python is one of the easiest computer programming languages to learn and use, with simple syntax and easy rules to follow. While it is aimed at beginners to Python coding, this book can also be used as a reference for those with a little more experience who want to brush up on their skills.",
        "title": "Python (Python basics for Beginners)",
        "author": "",
        "image": "https://shopping-phinf.pstatic.net/main_3246038/32460387998.20220519153948.jpg",
        "isbn": "9781955786331",
        "discount": "45600",
        "link": "https://search.shopping.naver.com/book/catalog/32460387998",
        "pubdate": "20210801"
    },
    {
        "publisher": "Ladoo Publishing LLC",
        "description": "Are you thinking about learning how to use the Python programming language? Thinking about getting started on a programming career?Python is one of the easiest computer programming languages to learn and use, with simple syntax and easy rules to follow. While it is aimed at beginners to Python coding, this book can also be used as a reference for those with a little more experience who want to brush up on their skills.",
        "title": "Python (This book includes : Python basics for Beginners + Python Automation Techniques And Web Scraping + Python For Data Science And Machine Learning)",
        "author": "",
        "image": "https://shopping-phinf.pstatic.net/main_3244493/32444933337.20220518215801.jpg",
        "isbn": "9781955786324",
        "discount": "109480",
        "link": "https://search.shopping.naver.com/book/catalog/32444933337",
        "pubdate": "20210730"
    },
    {
        "publisher": "Smart Digital Performance Ltd",
        "description": "★ ★ ★ 55% OFF for Bookstores! ★ ?★ ★Do you want to stop worrying about writing your own codes to create a strong program?Are you feeling overwhelmed about spending hours over a book and just getting confused again and again?If you want to learn the easiest way to deal with Python programming language, then keep reading...",
        "title": "Python (2 Books in 1. Python For Beginners, Machine Learning for Beginners. The Ultimate Beginners Guide to Python Programming and Machine Learning From Beginners to Expert Concepts)",
        "author": "",
        "image": "https://shopping-phinf.pstatic.net/main_5144741/51447417752.20250302084448.jpg",
        "isbn": "9781802347975",
        "discount": "0",
        "link": "https://search.shopping.naver.com/book/catalog/51447417752",
        "pubdate": "20210412"
    },
    {
        "publisher": "diomede ienna",
        "description": "Do you know what Python is?Python programming has become one of the most common programming languages people use. It brings a live language that can be used in software into the coding world. It has become the most common program used in websites and other digitalized materials. It helps one understand machines and any coded messages in any software that is already being used. There are many more programs, but this has been targeted for this book.",
        "title": "PYTHON (The Complete Crash Course to Learn Python in One Week Machine Learning and Deep Learning with Python with Hands-On Exercises)",
        "author": "",
        "image": "https://shopping-phinf.pstatic.net/main_5144604/51446048997.20250324074409.jpg",
        "isbn": "9781801548366",
        "discount": "0",
        "link": "https://search.shopping.naver.com/book/catalog/51446048997",
        "pubdate": "20210321"
    },
    {
        "publisher": "diomede ienna",
        "description": "Do you know what Python is?Python programming has become one of the most common programming languages people use. It brings a live language that can be used in software into the coding world. It has become the most common program used in websites and other digitalized materials. It helps one understand machines and any coded messages in any software that is already being used. There are many more programs, but this has been targeted for this book.",
        "title": "PYTHON (The Complete Crash Course to Learn Python in One Week Machine Learning and Deep Learning with Python with Hands-On Exercises)",
        "author": "",
        "image": "https://shopping-phinf.pstatic.net/main_5144663/51446635643.20250324074105.jpg",
        "isbn": "9781801548458",
        "discount": "0",
        "link": "https://search.shopping.naver.com/book/catalog/51446635643",
        "pubdate": "20210317"
    },
    {
        "publisher": "Mikcorp Ltd.",
        "description": "Includes 3 manuscriptsLearn Python Programming?In today's Industry, Python Programming is highly recommended for developing Websites. The creator of this programming language was Guido Van Rossum, released first in the year 1991.",
        "title": "Python",
        "author": "",
        "image": "https://shopping-phinf.pstatic.net/main_5144775/51447750170.20250317072531.jpg",
        "isbn": "9781801571296",
        "discount": "0",
        "link": "https://search.shopping.naver.com/book/catalog/51447750170",
        "pubdate": "20201228"
    },
    {
        "publisher": "Davide Cicatiello",
        "description": "DescriptionAre you one of those individuals who want to learn more about machine learning using Python? Perhaps you are seeking a detailed guide explaining how you can manage machine learning easily and hassle-free. Then look no further because this book, Machine Learning Using Python: Discover The World Of Machine Learning Using Python Algorithm Analysis, Ide, and Libraries.",
        "title": "Python",
        "author": "",
        "image": "https://shopping-phinf.pstatic.net/main_3254940/32549401534.20220523190535.jpg",
        "isbn": "9781801157032",
        "discount": "52900",
        "link": "https://search.shopping.naver.com/book/catalog/32549401534",
        "pubdate": "20201102"
    },
    {
        "publisher": "Dia Thabet",
        "description": "Have you always wanted to learn computer programming but are afraid it'll be too difficult for you? Or perhaps you know other programming languages but are interested in learning the Python language fast?? Then this guide is for you.",
        "title": "Python (Learn Python Programming in One Week with Step-by-Step Tutorials:  Learn Python Programming in One Week with Step-by-Step Tutorials)",
        "author": "",
        "image": "https://shopping-phinf.pstatic.net/main_5144740/51447407416.20250324072003.jpg",
        "isbn": "9798644385539",
        "discount": "0",
        "link": "https://search.shopping.naver.com/book/catalog/51447407416",
        "pubdate": "20200508"
    },
    {
        "publisher": "한빛미디어",
        "description": "고유한 기법으로 파이썬 언어를 가르치는 실용 안내서 『헤드 퍼스트 파이썬』. 파이썬에서 제공하는 함수 모듈, 데이터 마이닝, 데이터 랭글링 등의 기법을 다양한 예제를 통해 쉽고 빠르게 익히도록 도와준다. 파이썬의 기초를 간단히 살펴보고 영속성, 예외 처리, 웹 개발, SQLite, 데이터 마이닝, 구글 앱 엔진을 적용한다. 또한 안드로이드용 웹앱도 만들어 본다. 파이썬 프로그래머가 되기 위해 경험해야 할 모든 것을 가르쳐주는 책이다.",
        "title": "Python (머리에 쏙쏙 들어오는 파이썬 안내서)",
        "author": "폴 배리",
        "image": "https://shopping-phinf.pstatic.net/main_3249337/32493375826.20220527024016.jpg",
        "isbn": "9788979148688",
        "discount": "0",
        "link": "https://search.shopping.naver.com/book/catalog/32493375826",
        "pubdate": "20111028"
    },
    {
        "publisher": "Peachpit Press",
        "description": "The quick and easy way to master Python for Internet and Intranet programming with this visual, step-by-step guide to the popular Python programming language. This guide contains cross-platform coverage for the Mac, Windows, and Unix environments ...",
        "title": "Python (Visual QuickStart Guide)",
        "author": "",
        "image": "https://shopping-phinf.pstatic.net/main_3252253/32522535628.20220522130214.jpg",
        "isbn": "9780201748840",
        "discount": "32900",
        "link": "https://search.shopping.naver.com/book/catalog/32522535628",
        "pubdate": "20011001"
    },
    {
        "publisher": "Caboodle Books",
        "description": "Age range 6 to 9Daniel is scared of two things - the three-metre long python that his dad keeps in their loft and the Kelly Horton gang. He has nightmares that the snake escapes from the loft, wraps itself around him and starts to squeeze. Kelly Horton and her gang give him nightmares of a different kind.",
        "title": "Python (The Road to Driving Confidence)",
        "author": "",
        "image": "https://shopping-phinf.pstatic.net/main_5144604/51446042699.20250330072932.jpg",
        "isbn": "9780956948205",
        "discount": "0",
        "link": "https://search.shopping.naver.com/book/catalog/51446042699",
        "pubdate": "20111001"
    },
    {
        "publisher": "부크크(bookk)",
        "description": "\"Python 리터러시\"는 파이썬 입문서와 함께 공부하는 파이썬 연습문제입니다.　파이썬은 언어입니다. 파이썬은 컴퓨터를 사용하는 단순한 도구가 아닙니다. Python으로 작성된 코드는 컴퓨터에게 일을 지시하는 수단에 그치지 않습니다. 문제를 함께 해결하고자 하는 동료들과의 소통 수단이기도 합니다. 그래서 가독성이 좋은 코드의 조건 중 하나가 됩니다. 이는 파이썬이 언어라는 확실한 근거가 됩니다.　언어의 학습에서는 이해와 숙달이 함께 필요합니다. 파이썬이라는 언어를 학습할 때도 마찬가지입니다. 사고력과 끈기를 키워야 합니다. 그래서 연습문제가 필요합니다. 이것이 문해력을 뜻하는 ‘리터러시’라는 단어를 연습문제 책 이름에 넣은 이유입니다. 파이썬 입문서와 함께 공부하며 언어로서의 파이썬의 기본기를 다질 수 있도록 도울 수 있는 문제들을 이 책, \"Python 리터러시\"에 담았습니다.",
        "title": "Python 리터러시",
        "author": "민상준",
        "image": "https://shopping-phinf.pstatic.net/main_5252057/52520570819.20250201071422.jpg",
        "isbn": "9791141970338",
        "discount": "19200",
        "link": "https://search.shopping.naver.com/book/catalog/52520570819",
        "pubdate": "20241230"
    },
    {
        "publisher": "학산미디어",
        "description": "이 책은 수치해석에 대한 최신의 경향을 따라가기 위해서, 수학적 배경, 알고리즘, 프로그래밍 기법을 한 곳에 모아 놓은 책이다. 따라서, 독자들의 다양한 필요에 따라서 적절한 내용을 체계적으로 학습할 수 있도록 배려하였다. 이 책은 특별히 알고리즘의 작동 원리를 설명하는데 중점을 두었다. 프로그램을 수행하기 위해서는 작동 원리를 반드시 이해해야 하기 때문이다. 독자들이 수치해석에 대한 기본적인 지식을 충분히 습득할 수 있도록 다음과 같은 주안점을 두어 필요한 내용들을 소개하고 있다.1. 수학적 이론을 지양하고 보다 쉽게 수치해석의 원리를 이해할 수 있도록 내용을 상세히 풀어서 설명하였다.2. 알고리즘의 작동원리를 구체적으로 설명하여 이해하기 쉽도록 하였다.3. 알고리즘을 실제로 구현하기 위한 프로그래밍 기법을 복잡하지 않으면서도 체계적으로 설명하였다.",
        "title": "알고리즘으로 배우는 수치해석: Python 활용 (Python 활용)",
        "author": "최덕기",
        "image": "https://shopping-phinf.pstatic.net/main_3451290/34512901621.20230131164607.jpg",
        "isbn": "9791185294377",
        "discount": "28500",
        "link": "https://search.shopping.naver.com/book/catalog/34512901621",
        "pubdate": "20220915"
    },
    {
        "publisher": "자유아카데미",
        "description": "수학과 컴퓨팅이 데이터 과학에서 중요한 두 요소라는 것이 저자의 소신이다. 그렇지만 고급 수학을 전제하지 않는다. 낮은 수준에서부터도 수학적으로 접근하는 태도가 데이터 과학을 학습하고 전개함에 있어 중요하다. 컴퓨팅도 수학 못지않게 중요하다. 사용자 코딩을 해봐야 자신의 이해가 확실한지를 알 수 있다. 이 책에서는 대부분 예제에서 R과 Python을 활용하였다. 사용된 코드들은 출판사(자유아카데미) 홈페이지 http://www.freeaca.com에서 내려받을 수 있다.",
        "title": "데이터과학을 위한 확률.통계: R과 Python의 활용 (R과 Python의 활용)",
        "author": "허명회",
        "image": "https://shopping-phinf.pstatic.net/main_4981596/49815960649.20240817091325.jpg",
        "isbn": "9791158086305",
        "discount": "22080",
        "link": "https://search.shopping.naver.com/book/catalog/49815960649",
        "pubdate": "20240820"
    },
    {
        "publisher": "Michael Driscoll",
        "description": "Learn how to program with Python 3 from beginning to end. My book is made primarily for beginners. However, at least two-thirds of it is aimed at intermediate programmers. You may be wondering how that works. The book will be split into five parts: beginner material, the Python standard library, intermediate topics, 3rd party modules, and distribution.",
        "title": "Python 101",
        "author": "",
        "image": "https://shopping-phinf.pstatic.net/main_5144656/51446562000.20250127073413.jpg",
        "isbn": "9780996062817",
        "discount": "0",
        "link": "https://search.shopping.naver.com/book/catalog/51446562000",
        "pubdate": "20140603"
    },
    {
        "publisher": "한국금융연수원",
        "description": "통계와 데이터분석은 금융권 업무와 동떨어져 있고, 극소수의 사람만 알면 되는 그다지 쓸모없는 지식인 것처럼 여겨지던 때가 있었습니다. 그러나 지금은 데이터의 시대이고 빅데이터 분석과 활용이 화두가 될 정도로 상황이 많이 바뀌었습니다. 여기저기에서 통계와 데이터분석을 배우지 않으면 남들보다 뒤처질 것처럼 얘기하다 보니 왠지 꼭 배워야만 할 것 같은 분위기가 형성된 것 같습니다. 이러한 분위기 속에서 통계를 분석 도구로 사용하고 이를 가르치는 입장에서 보면, 너무 급하게 암기식으로 배우거나 현란한 공식에 매몰되어 흥미를 잃고, 실제 데이터를 접했을 때 전혀 적용하지 못하거나 잘못 적용하는 상황을 자주 목격하게 되었습니다.실무에서 통계를 적용하여 데이터를 분석할 때 컴퓨터 분석 도구를 활용하게 됩니다. 이 책에서는 대중의 접근성을 높이고자 무료로 사용 가능한 프로그래밍 언어인 R과 Python을 사용하였습니다. R과 Python을 사용하기 위한 프로그램 설치 및 설정, 기본 사용법부터 시작하여 데이터 준비 - 탐색 - 분석 단계까지 기술하였습니다. R과 Python 언어는 각기 장점을 가지고 있고 사용하는 사람의 배경에 따라 좀 더 편하고 익숙한 언어가 있을 수 있습니다. 하지만 대부분 실무 업무를 하다 보면 분석하는 사람의 숙련도나 선호도가 아닌 소속 기관이나 부서에 따라 언어를 선택하고 분석하게 되는 상황이 많아 이 책에서는 동일한 작업에 대해 두 언어를 모두 사용하였습니다. 통계적인 지식을 가지고 있고 프로그램 경험이 있더라도 R과 Python 중 하나의 언어에만 익숙한 경우 이 책을 활용한다면 짧은 시간에 다른 언어를 습득하는 데 도움이 될 것입니다.이 책은 통계와 프로그래밍 지식이 거의 없거나 기본적인 내용을 배운 적이 있지만 제대로 이해하지 못하고 여전히 어려움을 느끼고 있는 독자들을 위해 썼습니다. 이 책의 목적은 다양한 배경을 가진 독자들이 기본적인 데이터분석을 할 수 있도록 하는 것입니다. 데이터분석 기초 수업을 들으면서 보조 교재로 사용한다면 수업 중 이해가 되지 않는 부분들을 다시 짚고 넘어갈 수 있을 것입니다. 책에 포함된 R과 Python 코드들과 데이터, 그리고 버전의 업그레이드에 따른 수정 내용들은https://github.com/data-june-yoon/book에서 제공됩니다. 이 책의 많은 그래프가 명암으로만 표현되어 있지만 실제로는 훨씬 색이 다양하고 심미성이 높으니 직접 데이터와 코드를 활용하여 실습을 해보기를 바랍니다. 또한 책에 대한 의견이나 질문은 저자의 이메일(juneyoon@kbi.or.kr)로 공유하면 됩니다.높은 수준의 분석을 이해하기 위해서는 통계의 기반이 되는 수학부터 차근차근 시작하여 제대로 배우고 대학원 공부까지 하는 것이 가장 바람직할 것입니다. 하지만 그러지 못하는 독자들(학습자 포함)을 위해서 수학적인 내용을 많이 덜어내고 최대한 간결하고 직관적으로 설명하려고 하였습니다. 이 책의 후반부에 포함된 통계모형 부분에서도 각 분석 방법의 적용이 가능한 데이터 형태를 이해하고 프로그램을 적용하는 것에 초점을 맞추었습니다. 다만, 분산분석, 회귀분석, 로지스틱 회귀분석을 실무 프로젝트에서 활용해야 한다면 이 책을 기반으로 하여 보다 깊이 있는 교재를 활용하여 추가로 공부할 것을 권장합니다. 미리 겁을 먹고 통계와 데이터분석을 기피할 필요는 없지만, 분석 과정에서 모형에서의 가정이 맞는지 등은 언제나 조심스럽게 점검할 필요가 있습니다.〈br〉〈br〉이 책을 통해 좀 더 많은 사람들이 R과 Python을 활용한 데이터분석의 매력과 재미에 빠져들기를 바랍니다.",
        "title": "처음 만나는 통계와 데이터분석: R과 Python 활용 (R과 Python 활용)",
        "author": "윤정연",
        "image": "https://shopping-phinf.pstatic.net/main_3248771/32487713988.20240423080356.jpg",
        "isbn": "9788928726943",
        "discount": "0",
        "link": "https://search.shopping.naver.com/book/catalog/32487713988",
        "pubdate": "20220314"
    },
    {
        "publisher": "인피니티북스",
        "description": "『파이썬(Python) 3』은 쉽고 강력한 프로그래밍 언어인 파이썬에 대한 책이다. 파이썬의 기초, 시쿨리, 안드로이드 환경에서의 파이썬 스크립팅, 파이썬을 사용한 문자열 다루기, 다양한 파이썬 패키지의 소개와 다루는 법, 자이썬 등을 다룬다.",
        "title": "파이썬(Python) 3 (쉽고 재미있는 프로그래밍 언어)",
        "author": "최용",
        "image": "https://shopping-phinf.pstatic.net/main_3244164/32441643782.20231017082827.jpg",
        "isbn": "9791185578002",
        "discount": "22500",
        "link": "https://search.shopping.naver.com/book/catalog/32441643782",
        "pubdate": "20140212"
    },
    {
        "publisher": "부크크(Bookk)",
        "description": "파이썬을 배우기 위해 여러권의 책이 필요 없습니다. 파이썬에 관한 단 한권의 책을 선택해야 한다면 이 책입니다. 프로그래밍 언어와 코딩을 배우길 원하는 사람, 파이썬 애플리케이션을 만들고 싶은 사람, 머신러닝으로 데이터를 분석하고 싶은사람, 파이썬은 이 모두에게 필요합니다. 이 책은 파이썬 프로그래밍 언어의 개념을 확실히 심어줍니다.",
        "title": "The Python (파이썬 프로그래밍)",
        "author": "허진경",
        "image": "https://shopping-phinf.pstatic.net/main_3246700/32467009890.20220519232556.jpg",
        "isbn": "9791127251765",
        "discount": "0",
        "link": "https://search.shopping.naver.com/book/catalog/32467009890",
        "pubdate": "20181113"
    },
    {
        "publisher": "햄큐(HAMQ)",
        "description": "『비트코딩 Python』은 문제은행식 코딩 문제집으로 총 516문항을 수록하였다. 또한 각 단원마다 난이도 별 연습문제로 개념을 확실하게 잡을 수 있도록 구성하였으며, 다양한 영역과 다양한 주제의 신선한 문제를 삽입하였다. 이 교재는 처음 코딩을 배우는 학생, 코딩 수업을 듣는 학생, 코딩을 빠르게 하고 싶은 학생, 코딩공부를 해도 프로그램을 작성하는 것이 어려운 학생, 자료구조 등의 전공영역을 공부하기 전 코딩 실력이 부족하다 느끼는 학생들에게 도움이 될 것이다.",
        "title": "비트코딩 Python (최초의 문제은행식 코딩문제집)",
        "author": "박해민",
        "image": "https://shopping-phinf.pstatic.net/main_3248332/32483328687.20230421071136.jpg",
        "isbn": "9791196328832",
        "discount": "0",
        "link": "https://search.shopping.naver.com/book/catalog/32483328687",
        "pubdate": "20181019"
    },
    {
        "publisher": "Apress",
        "description": "Not only will this book help your code, it will also help you understand and interact with the many established Python communities, or even start your own. Take your Python knowledge and coding skills to the next level.",
        "title": "Pro Python",
        "author": "Marty Alchin",
        "image": "https://shopping-phinf.pstatic.net/main_3244404/32444045095.20220518202147.jpg",
        "isbn": "9781430227571",
        "discount": "82100",
        "link": "https://search.shopping.naver.com/book/catalog/32444045095",
        "pubdate": "20100601"
    },
    {
        "publisher": "Apress",
        "description": "Pro Python, Second Edition explores concepts and features normally left to experimentation, allowing you to be even more productive and creative.In addition to pure code concerns, Pro Python develops your programming techniques and approaches, which will help make you a better Python programmer.",
        "title": "Pro Python",
        "author": "",
        "image": "https://shopping-phinf.pstatic.net/main_3245680/32456801665.20220519120500.jpg",
        "isbn": "9781484203354",
        "discount": "82100",
        "link": "https://search.shopping.naver.com/book/catalog/32456801665",
        "pubdate": "20150107"
    },
    {
        "publisher": "지필미디어",
        "description": "AI와 데이터 과학의 시대가 도래하면서 방대한 데이터 속에서 의미 있는 통찰을 도출하는 능력은 그 어느 때보다 중요해지고 있습니다. 이러한 흐름 속에서도 전통적 통계분석에 대한 깊은 이해는 여전히 데이터 과학의 핵심을 이루고 있으며, 이를 뒷받침하는 도구로서의 통계 소프트웨어의 역할은 지속적으로 강조되고 있습니다. 기존 출간한 『Stata 기초적 이해와 활용』과 『Stata 기초통계와 회귀분석』에서는 Stata를 중심으로 통계분석의 기초부터 응용까지 체계적으로 다루어 왔습니다. 기존 책을 대신하여 본서 한 권으로 재편집하였고 데이터 과학의 최신 트렌드에 발맞추어 Python 코드도 함께 제시하였습니다. 이를 통해 독자들은 Stata의 강력한 기능을 활용함과 동시에 Python의 유연성과 확장성을 경험할 수 있을 것으로 기대합니다. 데이터 과학은 단순한 통계분석을 넘어 머신러닝, 인공지능 등 다양한 분야와 융합되고 있습니다. 그럼에도 불구하고, 통계학의 기초적인 원리와 분석 기법에 대한 탄탄한 이해는 데이터 과학자가 복잡한 문제를 해결하고, 신뢰할 수 있는 결과를 도출 하는 데 필수적입니다. 본서는 이러한 배경을 바탕으로 Stata와 Python을 효과적으로 활용하여 실질적인 데이터 분석 능력을 배양하는 데 중점을 두었습니다.본서에서는 Stata와 Python을 활용한 통계분석의 기초부터 심화까지 포괄적으로 다루고자 합니다. 데이터 불러오기와 저장, 데이터 관리 명령어, 기초 통계량 계산, 데이터 시각화, 가설 검정, 회귀분석 등 데이터 과학자가 실무에서 필요로 하는 다양한 분석 기법과 방법론을 체계적으로 소개하고 있습니다. 실습을 통해 직접적인 경험을 쌓을 수 있도록 다양한 예제와 코드를 포함하였습니다.",
        "title": "데이터과학자를 위한 통계분석 STATA  Python (STATA & Python)",
        "author": "민인식^최필선",
        "image": "https://shopping-phinf.pstatic.net/main_5109301/51093011620.20241030071005.jpg",
        "isbn": "9791193187623",
        "discount": "30400",
        "link": "https://search.shopping.naver.com/book/catalog/51093011620",
        "pubdate": "20241030"
    },
    {
        "publisher": "홍릉",
        "description": "알고리즘 공부를 위한 실전적 자료구조",
        "title": "PYTHON으로 배우는 자료구조",
        "author": "홍지만^한정규^민홍^정진만^이재흥^장준혁^허준영",
        "image": "https://shopping-phinf.pstatic.net/main_5188540/51885409619.20241212005425.jpg",
        "isbn": "9791156002321",
        "discount": "26600",
        "link": "https://search.shopping.naver.com/book/catalog/51885409619",
        "pubdate": "20241130"
    },
    {
        "publisher": "자유아카데미",
        "description": "이 책은 성신여자대학교에서 “빅데이터의 이해와 활용”을 가르치면서 쓴 강의 텍스트 〈빅 데이터의 과학: R Commander의 활용〉의 고급 버전입니다. 이 책에서는 계산 도구(computing tools)로 R Commander 대신 R과 Python을 사용하였습니다.  R과 Python은 데이터 과학 커뮤니티에서 활용되는 Top 2 컴퓨터 언어입니다. R은 전통적으로 통계학 배경의 전공자들이 사용하였고, Python은 컴퓨터 전공자들이 사용하였습니다. 두 언어가 기질적인 차이가 있어서 개인별로 선호가 다릅니다만, 선호의 차이는 주로 어느 언어를 먼저 배우느냐에 있어 보입니다. 한국어를 영어보다 먼저 배운 사람은 한국어가 편하고, 영어를 한국어보다 먼저 배운 사람은 영어가 편한 것과 마찬가지입니다. 이 책에서는 R과 Python을 동시에 제시함으로써 두 언어에 대한 비차별적 습득을 도모합니다. 물론 한 가지를 선택하여 학습할 수도 있습니다.  이 책은 10개의 장으로 구성되어 있습니다. ‘빅’ 데이터 입문에서 시작하여, 수치형 데이터의 탐색, 변수변환, 범주형 데이터의 탐색, 통계적 추론, 회귀모형, 분류모형, 군집화 등의 기본 방법론을 8개의 장에 넣었습니다. 그리고 마지막 2개의 장에 기계학습(machine learning)의 맛보기라고 할 수 있는 k-NN과 나무모형(tree models)에 관한 내용을 수록하였습니다.",
        "title": "데이터 과학 입문: R과 Python의 활용 (R과 Python의 활용)",
        "author": "허명회",
        "image": "https://shopping-phinf.pstatic.net/main_3246221/32462212607.20230214163948.jpg",
        "isbn": "9791158083229",
        "discount": "19000",
        "link": "https://search.shopping.naver.com/book/catalog/32462212607",
        "pubdate": "20210925"
    },
    {
        "publisher": "상학당",
        "description": "『Python 프로그래밍』은 〈스마트로봇 EV3의 개요 및 구성〉, 〈파이썬의 개요 및 설정〉, 〈파이썬 프로그램 작성과 실행〉 등이 수록되어 있다.",
        "title": "Python 프로그래밍 (스마트로봇 EV3를 활용한)",
        "author": "남상엽",
        "image": "https://shopping-phinf.pstatic.net/main_3249023/32490237759.20230920071451.jpg",
        "isbn": "9788965872023",
        "discount": "28500",
        "link": "https://search.shopping.naver.com/book/catalog/32490237759",
        "pubdate": "20200915"
    },
    {
        "publisher": "Springer",
        "description": "This easy-to-understand textbook presents a modern approach to learning numerical methods (or scientific computing), with a unique focus on the modeling and applications of the mathematical content.",
        "title": "Applied Scientific Computing 양장본 Hardcover (With Python)",
        "author": "Peter R. Turner^Thomas Arildsen^Kathleen Kavanagh",
        "image": "https://shopping-phinf.pstatic.net/main_3530170/35301701009.20221018153534.jpg",
        "isbn": "9783319895741",
        "discount": "98530",
        "link": "https://search.shopping.naver.com/book/catalog/35301701009",
        "pubdate": "20180731"
    },
    {
        "publisher": "Springer Nature B.V.",
        "description": "This easy-to-understand textbook presents a modern approach to learning numerical methods (or scientific computing), with a unique focus on the modeling and applications of the mathematical content. Emphasis is placed on the need for, and methods of, scientific computing for a range of different types of problems, supplying the evidence and justification to motivate the reader. Practical guidance on coding the methods is also provided, through simple-to-follow examples using Python.",
        "title": "Applied Scientific Computing (With Python)",
        "author": "",
        "image": "https://shopping-phinf.pstatic.net/main_4734273/47342735766.20240429071623.jpg",
        "isbn": "9783319895765",
        "discount": "72980",
        "link": "https://search.shopping.naver.com/book/catalog/47342735766",
        "pubdate": "20180723"
    },
    {
        "publisher": "퍼플",
        "description": "4차 산업 혁명 시대의 중심에 서 있는 현대인들에게 프로그래밍 언어를 배워 프로그램을 직접 만들어 보고 작동 방식 및 의미를 이해하는 것은 중요하고 필수 불가결한 요소가 되었다. 하지만 현재의 프로그래밍 언어 교재들은 비록 자연 언어와 유사한 고급 프로그래밍 언어라 할 지라도 컴퓨터 전공자를 대상으로 언어의 문법 설명에 초점이 맞추어져 있다. 일반인 또는 중고등학생과 같은 컴퓨터 비전공자가 처음 프로그래밍 언어를 배우기에는 어려운 점이 있고 코딩에 대한 관심과 열정을 이끌어 내기에 부족한 점이 많다. 이에 코딩을 통해 달성하고자 하는 논리적 사고력 및 문제해결 능력 배양을 우선 순위에 두고 활용할 수 있는 쉬운 프로그래밍 언어를 사용하고 문제 해결을 위한 코딩 위주로 구성된 교재의 개발에 필요성을 느껴 이 책을 쓰게 되었다.코딩에 처음 입문하고자 하는 경우 복잡한 문법 구조를 가진 어려운 프로그래밍 언어를 선택하기 보다는 배우기 쉬우면서도 다양한 영역에 활용이 가능한 프로그래밍 언어를 선택하는 것이 중요하다. 이에 여기서는 Python 언어를 선택하였으며 문법 구조를 익히기에 적합한 문제들을 제시하고 이러한 문제들을 해결하기 위한 풀이 과정을 연구하여 이를 코딩으로 표현하는 절차를 지향하고 있다. 문제 해결을 위한 코딩으로 자연스럽게 언어의 문법 구조를 익혀 나가는 방식으로 책의 내용을 구성하였다.이 책은 컴퓨터 코딩에 관심 있는 일반인뿐만 아니라 컴퓨터 전공자의 코딩 입문서로 활용이 가능하다. 교재 활용을 통해 Python 언어의 문법 구조에 자연스럽게 숙달될 수 있고 학습자들이 코딩에 대해 갖는 두려움을 없앨 수 있다. 꾸준한 코딩 연습을 통해 향후 Python을 활용한 다양한 응용 분야의 프로그래밍에 대한 기초를 다질 수 있다.",
        "title": "Python 프로그래밍",
        "author": "서문석",
        "image": "https://shopping-phinf.pstatic.net/main_3381210/33812107743.20221230072150.jpg",
        "isbn": "9788924046915",
        "discount": "11500",
        "link": "https://search.shopping.naver.com/book/catalog/33812107743",
        "pubdate": "20170330"
    },
    {
        "publisher": "開拓社",
        "description": "",
        "title": "言語硏究のためのPython活用術",
        "author": "淺尾仁彦 著",
        "image": "https://shopping-phinf.pstatic.net/main_5338716/53387169518.20250306084741.jpg",
        "isbn": "9784758924108",
        "discount": "31920",
        "link": "https://search.shopping.naver.com/book/catalog/53387169518",
        "pubdate": "20250109"
    },
    {
        "publisher": "한국금융연수원",
        "description": "통계와 데이터분석은 금융권 업무와 동떨어져 있고, 극소수의 사람만 알면 되는 그다지 쓸모없는 지식인 것처럼 여겨지던 때가 있었습니다. 그러나 지금은 데이터의 시대이고 빅데이터 분석과 활용이 화두가 될 정도로 상황이 많이 바뀌었습니다. 여기저기에서 통계와 데이터분석을 배우지 않으면 남들보다 뒤처질 것처럼 얘기하다 보니 왠지 꼭 배워야만 할 것 같은 분위기가 형성된 것 같습니다. 이러한 분위기 속에서 통계를 분석 도구로 사용하고 이를 가르치는 입장에서 보면, 너무 급하게 암기식으로 배우거나 현란한 공식에 매몰되어 흥미를 잃고, 실제 데이터를 접했을 때 전혀 적용하지 못하거나 잘못 적용하는 상황을 자주 목격하게 되었습니다.",
        "title": "처음 만나는 통계와 데이터분석: R과 Python 활용 (R과 Python 활용, 제2판)",
        "author": "윤정연",
        "image": "https://shopping-phinf.pstatic.net/main_4678931/46789317618.20240402080549.jpg",
        "isbn": "9788928781959",
        "discount": "18900",
        "link": "https://search.shopping.naver.com/book/catalog/46789317618",
        "pubdate": "20240401"
    },
    {
        "publisher": "르네싸이",
        "description": "통계학은 자료를 수집하고 유용한 정보를 추출하며 합리적인 의사결정에 필요한 통계 기법들을 배우는 학문으로, 이를 통해 다양한 통계 기법에 대한 정확한 이해와 적용 및 통계분석 결과를 해석하는 능력을 배운다. 효율적인 의사결정을 위해서는 무엇보다 통계학의 기본개념과 통계 분석기법의 기본원리에 대한 이해 및 실제 자료에 대한 응용 능력이 함께 보유되어야 한다. 또한 방대한 자료와 통계 기법의 신속한 수행을 위해 통계학 수업에는 반드시 통계패키지의 사용이 병행되어야 한다. 현재 사용되고 있는 통계패키지에는 다양한 종류들이 있으나, 본 교재에서는 딥러닝, 머신러닝, 인공지능 등 데이터사이언스 분야에서 그 역할을 확장하고 있는 통계용 언어인 Python을 사용하였다. 본 교재는 각 장의 뒷부분에 해당 장에서 언급된 통계 기법들을 통계패키지 Python을 이용하여 실습할 수 있는 실습 문제들을 실었다.",
        "title": "데이터사이언스를 위한 기초통계학 (python을 이용한 데이터 분석)",
        "author": "김형우",
        "image": "https://shopping-phinf.pstatic.net/main_5013010/50130106619.20241003071351.jpg",
        "isbn": "9791193143070",
        "discount": "34650",
        "link": "https://search.shopping.naver.com/book/catalog/50130106619",
        "pubdate": "20240830"
    },
    {
        "publisher": "경문사",
        "description": "데이터가 있는 곳에 통계가 있다!빅데이터의 활용으로 4차 산업혁명 시대인 현대 사회에서 통계학은 필수적인 분석도구라 할 수 있다. 그러나 통계학을 배우거나 사용하려는 사람들에게는 통계학이 어렵고 진입장벽이 높다고 느껴지는 것이 일반적이다. 이 책은 통계학의 기본 개념과 용어, 통계적 사고 방법을 쉽게 받아들일 수 있게 도와주고, 통계학을 배우는 학생들의 눈높이에 맞춰 개념을 정립할 수 있도록 하였다.또한 최근 각광받고 있는 통계패키지인 R과 Python을 활용하여 통계학의 이론적인 수식에 의거한 문제 해결과 함께 프로그램을 활용하여 원하는 문제를 해결할 수 있도록 실질적 활용 예제를 각 장마다 배치하여 배운 이론을 실제 프로그램에 적용할 수 있도록 하였다.",
        "title": "기초통계플러스알파 (R과 Python을 활용한)",
        "author": "김명준^김영화^박영호",
        "image": "https://shopping-phinf.pstatic.net/main_3817746/38177463620.20230927071317.jpg",
        "isbn": "9791160736090",
        "discount": "28500",
        "link": "https://search.shopping.naver.com/book/catalog/38177463620",
        "pubdate": "20230302"
    },
    {
        "publisher": "Python Press",
        "description": "A down-to-earth and fun look at saving the planet one household at a time, with 130 plant profiles, 52 recipes, 294 photos, poetry and more.",
        "title": "Peasant in Paradise: four seasons eco-living",
        "author": "",
        "image": "https://shopping-phinf.pstatic.net/main_3313752/33137529933.20220625201434.jpg",
        "isbn": "9780645285406",
        "discount": "52370",
        "link": "https://search.shopping.naver.com/book/catalog/33137529933",
        "pubdate": "20210915"
    },
    {
        "publisher": "Big Book Ltd",
        "description": "Do you want to become a coding & programming expert in no time? This guide will teach you how!Are you interested in coding, programming, and artificial intelligence?Would you like to learn Python, but you have no idea how to start?This guide is the answer to all your problems!(This is the color version of the book)Python is one of the top 10 popular programming languages, and it can be used to developing desktop GUI applications, websites, and web applications.",
        "title": "Learn Python (Get Started Now with Our Beginner’s Guide to Coding, Programming, and Understanding Artificial Intelligence in the Fastest-Growing Machine Learning Language)",
        "author": "",
        "image": "https://shopping-phinf.pstatic.net/main_3253876/32538760423.20220523091128.jpg",
        "isbn": "9781914065606",
        "discount": "61960",
        "link": "https://search.shopping.naver.com/book/catalog/32538760423",
        "pubdate": "20210226"
    },
    {
        "publisher": "Big Book Ltd",
        "description": "Do you want to become a coding & programming expert in no time? This guide will teach you how!Are you interested in coding, programming, and artificial intelligence?Would you like to learn Python, but you have no idea how to start?This guide is the answer to all your problems!(This is the color version of the book)Python is one of the top 10 popular programming languages, and it can be used to developing desktop GUI applications, websites, and web applications.",
        "title": "Learn Python (Get Started Now with Our Beginner’s Guide to Coding, Programming, and Understanding Artificial Intelligence in the Fastest-Growing Machine Learning Language)",
        "author": "Adams, Anthony",
        "image": "https://shopping-phinf.pstatic.net/main_3253379/32533799305.20220523035303.jpg",
        "isbn": "9781914065590",
        "discount": "50340",
        "link": "https://search.shopping.naver.com/book/catalog/32533799305",
        "pubdate": "20210210"
    },
    {
        "publisher": "Big Book Ltd",
        "description": "Do you want to become a coding & programming expert in no time? This guide will teach you how!Are you interested in coding, programming, and artificial intelligence?Would you like to learn Python, but you have no idea how to start?This guide is the answer to all your problems!Python is one of the top 10 popular programming languages, and it can be used to developing desktop GUI applications, websites, and web applications.There are many reasons why learning Python is essential.",
        "title": "Learn Python (Get Started Now with Our Beginner’s Guide to Coding, Programming, and Understanding Artificial Intelligence in the Fastest-Growing Machine Learning Language)",
        "author": "",
        "image": "https://shopping-phinf.pstatic.net/main_3246652/32466521149.20220519213803.jpg",
        "isbn": "9781914065316",
        "discount": "67740",
        "link": "https://search.shopping.naver.com/book/catalog/32466521149",
        "pubdate": "20201224"
    },
    {
        "publisher": "Big Book Ltd",
        "description": "Do you want to become a coding & programming expert in no time? This guide will teach you how!Are you interested in coding, programming, and artificial intelligence?Would you like to learn Python, but you have no idea how to start?This guide is the answer to all your problems!Python is one of the top 10 popular programming languages, and it can be used to developing desktop GUI applications, websites, and web applications.There are many reasons why learning Python is essential.",
        "title": "Learn Python (Get Started Now with Our Beginner’s Guide to Coding, Programming, and Understanding Artificial Intelligence in the Fastest-Growing Machine Learning Language)",
        "author": "",
        "image": "https://shopping-phinf.pstatic.net/main_3249237/32492372782.20220520215855.jpg",
        "isbn": "9781914065088",
        "discount": "48370",
        "link": "https://search.shopping.naver.com/book/catalog/32492372782",
        "pubdate": "20201209"
    },
    {
        "publisher": "정익사",
        "description": "▶ 이 책은 컴퓨팅 사고를 다룬 이론서입니다. 컴퓨팅 사고의 기초적이고 전반적인 내용을 학습할 수 있습니다.",
        "title": "모두를 위한 컴퓨팅 사고 (Python 기초문법 수록)",
        "author": "김종완",
        "image": "https://shopping-phinf.pstatic.net/main_3249276/32492768151.20250325071419.jpg",
        "isbn": "9788935305445",
        "discount": "21850",
        "link": "https://search.shopping.naver.com/book/catalog/32492768151",
        "pubdate": "20200303"
    },
    {
        "publisher": "성안당",
        "description": "만화처럼 빨려 들어가는 비주얼한 프로그래밍 입문서 1학년 시리즈! 염소 박사님, 다솜 양과 함께라면 인공지능 앱도 뚝딱! 누구에게나 가볍고 쉬운 파이썬 입문서!",
        "title": "파이썬(Python): 1학년 (파이썬, 만화와 대화로 공부해 인공지능 앱까지 도전!)",
        "author": "모리 요시나오",
        "image": "https://shopping-phinf.pstatic.net/main_3246406/32464067569.20230321162109.jpg",
        "isbn": "9788931555684",
        "discount": "38500",
        "link": "https://search.shopping.naver.com/book/catalog/32464067569",
        "pubdate": "20181218"
    },
    {
        "publisher": "경문사",
        "description": "데이터가 있는 곳에 통계가 있다.현대 사회에서 넘쳐나는 테이터를 처리하기 위해서 통계학은 필수적인 분석 도구로 자리매김을 하고 있다. 또한 컴퓨터의 보급과 발달로, 과거에는 분석이 힘들던 대용량 데이터들도 분석이 가능해진지 오래다. 4차 산업혁명 시대, 빅데이터 시대라 불리는 현재, 불확실성은 점점 더 확대되어가고 있으며 그러한 불확실성을 해결하고자 하는 노력과 발전 또한 괄목할만한 성장을 하고 있는 요즈음 통계학은 이제 전공자만이 향유하는 학문의 선을 넘어 거의 모든 학문, 산업 분야에서 필수 불가결한 학문으로 적용 영역을 넓히며 활용되고 있다.",
        "title": "기초통계 플러스알파 (R과 Python을 활용한)",
        "author": "김명준^김영화^박영호",
        "image": "https://shopping-phinf.pstatic.net/main_3246007/32460076851.20221228072221.jpg",
        "isbn": "9791160733457",
        "discount": "0",
        "link": "https://search.shopping.naver.com/book/catalog/32460076851",
        "pubdate": "20200302"
    },
    {
        "publisher": "Springer Nature B.V.",
        "description": "Refine your programming techniques and approaches to become a more productive and creative Python programmer. This book explores the concepts and features that will improve not only your code but also your understanding of the Python community with insights and details about the Python philosophy.Pro Python 3, Third Edition gives you the tools to write clean, innovative code.",
        "title": "Pro Python 3 (Features and Tools for Professional Development)",
        "author": "",
        "image": "https://shopping-phinf.pstatic.net/main_4734056/47340568441.20240429071158.jpg",
        "isbn": "9781484243862",
        "discount": "72980",
        "link": "https://search.shopping.naver.com/book/catalog/47340568441",
        "pubdate": "20190321"
    },
    {
        "publisher": "학산미디어",
        "description": "▶ 이 책은 이공학도를 위한 수치해석에 대해 다룬 도서입니다. 수치해석의 기초적이고 전반적인 내용을 확인할 수 있도록 구성했습니다.",
        "title": "수치해석 (Python으로 코딩하기)",
        "author": "최덕기",
        "image": "https://shopping-phinf.pstatic.net/main_3243627/32436277659.20220527025512.jpg",
        "isbn": "9791185294216",
        "discount": "23750",
        "link": "https://search.shopping.naver.com/book/catalog/32436277659",
        "pubdate": "20170905"
    },
    {
        "publisher": "Python Press",
        "description": "Rendering or plastering is a craft as old as house building, the basic methods and concepts having changed little over time.  This book offers a detailed look at the use of raw earth for painting and rendering walls in new as well as in existing buildings, focusing on sand-clay render, straw-clay render and clay paints.",
        "title": "Earth Render - The Art of Clay Plaster, Render and Paints",
        "author": "Python Press",
        "image": "https://shopping-phinf.pstatic.net/main_3245327/32453270524.20220519092621.jpg",
        "isbn": "9780975778203",
        "discount": "49270",
        "link": "https://search.shopping.naver.com/book/catalog/32453270524",
        "pubdate": "20131004"
    },
    {
        "publisher": "Python Press",
        "description": "In this esoteric discourse by Australian geomancer Alanna Moore, we see how water conveys intelligence, vitality and healing to landscapes, as well as our own watery being. Found by water diviners in locations undreamed of by hydrologists, water's manifestations are often mysterious. The earliest sacred sites were connected to water and spiritual traditions flowed from them. The Wisdom of Water pays homage to water's role in landscapes, it's subtle energetic aspects and global folk traditions.",
        "title": "The Wisdom of Water",
        "author": "",
        "image": "https://shopping-phinf.pstatic.net/main_3246265/32462652418.20220519174445.jpg",
        "isbn": "9780975778210",
        "discount": "40150",
        "link": "https://search.shopping.naver.com/book/catalog/32462652418",
        "pubdate": "20071007"
    },
    {
        "publisher": "Python Press",
        "description": "Ancient standing stones transmit beneficial Earth energies and provide anchor points for the power and spirit of the land. Old traditions of healing, divination, wish fulfillment and fertility associated with certain stones continue to hold currency today. Anyone can tune into Earth's subtle dimensions with the art of dowsing and other forms of super-sensory attunement.",
        "title": "Touchstones for Today",
        "author": "",
        "image": "https://shopping-phinf.pstatic.net/main_3246648/32466489539.20220519213850.jpg",
        "isbn": "9780975778258",
        "discount": "36500",
        "link": "https://search.shopping.naver.com/book/catalog/32466489539",
        "pubdate": "20130216"
    },
    {
        "publisher": "Python Press",
        "description": "When architect Peter Cowman dreamed up his groundbreaking ‘Be Your Own Architect’ concept he quickly discovered that his university education had neglected to teach him the rudiments of house design! Realising that people had always practiced a ‘vernacular’ architecture he set out to revive this tradition. Vernacular styles of building are characterised by their simplicity, by their use of local materials and by the ease with which they can be constructed.",
        "title": "The Sheltermaker’s Manual - Volume 1",
        "author": "",
        "image": "https://shopping-phinf.pstatic.net/main_3250914/32509141499.20220521184329.jpg",
        "isbn": "9780975778265",
        "discount": "60220",
        "link": "https://search.shopping.naver.com/book/catalog/32509141499",
        "pubdate": "20130216"
    }
]